pybraads/__init__.py
pybraads/adsodbc.py
pybraads-0.1.7.dist-info/licenses/LICENSE
pybraads-0.1.7.dist-info/METADATA
pybraads-0.1.7.dist-info/WHEEL
pybraads-0.1.7.dist-info/RECORD
