Metadata-Version: 2.4
Name: pybraads
Version: 0.1.7
Summary: Brainstorming package, manage ODBC connexion to database Advantage Database.
License: MIT
License-File: LICENSE
Author: Brainstorming
Author-email: Support.erp@brainstorming.eu
Requires-Python: >=3.10,<4.0
Classifier: License :: OSI Approved :: MIT License
Classifier: Programming Language :: Python :: 3
Classifier: Programming Language :: Python :: 3.10
Classifier: Programming Language :: Python :: 3.11
Classifier: Programming Language :: Python :: 3.12
Classifier: Programming Language :: Python :: 3.13
Classifier: Programming Language :: Python :: 3.14
Requires-Dist: pybrastr (>=0.1.4,<0.2.0)
Requires-Dist: pyodbc (>=5.1.0,<6.0.0)
